[{"index": 6163, "id": "https://openalex.org/W3100151520", "doi": null, "title": "Solving the distance discrepancy for the open cluster NGC 2453. The planetary nebula NGC 2452 is not a cluster member", "display_name": "Solving the distance discrepancy for the open cluster NGC 2453. The planetary nebula NGC 2452 is not a cluster member", "publication_year": 2019, "publication_date": "2019-06-01", "ids": {"openalex": "https://openalex.org/W3100151520", "mag": "3100151520"}, "host_venue": {"id": "https://openalex.org/V205231332", "issn_l": "0004-6361", "issn": ["0004-6361", "1432-0746"], "display_name": "Astronomy and Astrophysics", "publisher": "EDP Sciences", "type": "publisher", "url": "https://doi.org/10.1051/0004-6361/201935243", "is_oa": true, "version": "publishedVersion", "license": null}, "type": "journal-article", "open_access": {"is_oa": true, "oa_status": "bronze", "oa_url": "https://www.aanda.org/articles/aa/pdf/2019/06/aa35243-19.pdf"}, "authorships": [{"author_position": "first", "author": {"id": "https://openalex.org/A2941665031", "display_name": "D. Gonz\u00e1lez-D\u00edaz", "orcid": "https://orcid.org/0000-0003-1698-4924"}, "institutions": [{"id": "https://openalex.org/I2802166871", "display_name": "Catholic University of the North", "ror": "https://ror.org/02akpm128", "country_code": "CL", "type": "education"}, {"id": "https://openalex.org/I35961687", "display_name": "University of Antioquia", "ror": "https://ror.org/03bp5hc83", "country_code": "CO", "type": "education"}], "raw_affiliation_string": "Instituto de Astronom\u00eda, Universidad Cat\u00f3lica del Norte, Av. Angamos 0610, Antofagasta, Chile"}, {"author_position": "middle", "author": {"id": "https://openalex.org/A3066436910", "display_name": "C. Moni Bidin", "orcid": null}, "institutions": [{"id": "https://openalex.org/I2802166871", "display_name": "Catholic University of the North", "ror": "https://ror.org/02akpm128", "country_code": "CL", "type": "education"}], "raw_affiliation_string": "[Instituto de Astronom\u00eda, Universidad Cat\u00f3lica del Norte, Av. Angamos 0610, Antofagasta, Chile]"}, {"author_position": "middle", "author": {"id": "https://openalex.org/A2339956464", "display_name": "E. Silva-Villa", "orcid": null}, "institutions": [{"id": "https://openalex.org/I35961687", "display_name": "University of Antioquia", "ror": "https://ror.org/03bp5hc83", "country_code": "CO", "type": "education"}], "raw_affiliation_string": "Instituto de F\u00edsica, Universidad de Antioquia (UdeA), Calle 70 52-21, Medell\u00edn, Colombia"}, {"author_position": "middle", "author": {"id": "https://openalex.org/A2270980489", "display_name": "Giovanni Carraro", "orcid": "https://orcid.org/0000-0002-0155-9434"}, "institutions": [{"id": "https://openalex.org/I4210159647", "display_name": "Osservatorio Astronomico di Padova", "ror": "https://ror.org/04z3y3f62", "country_code": "IT", "type": "facility"}], "raw_affiliation_string": "Dipartimento di Fisica e Astronomia, Universit\u00e0 di Padova, vicolo Osservatorio, 3, 35122, Padova, Italy"}, {"author_position": "middle", "author": {"id": "https://openalex.org/A712155626", "display_name": "Daniel J. Majaess", "orcid": null}, "institutions": [{"id": "https://openalex.org/I179301192", "display_name": "Mount Saint Vincent University", "ror": "https://ror.org/03g3p3b82", "country_code": "CA", "type": "education"}, {"id": "https://openalex.org/I66890659", "display_name": "Saint Mary's University", "ror": "https://ror.org/010zh7098", "country_code": "CA", "type": "education"}], "raw_affiliation_string": "Mount Saint Vincent University, Halifax, Nova Scotia, Canada"}, {"author_position": "middle", "author": {"id": "https://openalex.org/A2303389179", "display_name": "Andr\u00e9 Moitinho", "orcid": "https://orcid.org/0000-0003-0822-5995"}, "institutions": [{"id": "https://openalex.org/I141596103", "display_name": "University of Lisbon", "ror": "https://ror.org/01c27hj86", "country_code": "PT", "type": "education"}], "raw_affiliation_string": "SIM \u2013 Faculdade de Ci\u00eancias da Universidade de Lisboa, Ed. C8, Campo Grande, 1749-016 Lisboa, Portugal"}, {"author_position": "middle", "author": {"id": "https://openalex.org/A3104660245", "display_name": "C. Orquera-Rojas", "orcid": null}, "institutions": [{"id": "https://openalex.org/I2802166871", "display_name": "Catholic University of the North", "ror": "https://ror.org/02akpm128", "country_code": "CL", "type": "education"}], "raw_affiliation_string": "[Instituto de Astronom\u00eda, Universidad Cat\u00f3lica del Norte, Av. Angamos 0610, Antofagasta, Chile]"}, {"author_position": "middle", "author": {"id": "https://openalex.org/A2949987551", "display_name": "C. A. L. Morales Mar\u00edn", "orcid": null}, "institutions": [{"id": "https://openalex.org/I2802166871", "display_name": "Catholic University of the North", "ror": "https://ror.org/02akpm128", "country_code": "CL", "type": "education"}], "raw_affiliation_string": "[Instituto de Astronom\u00eda, Universidad Cat\u00f3lica del Norte, Av. Angamos 0610, Antofagasta, Chile]"}, {"author_position": "last", "author": {"id": "https://openalex.org/A2942499201", "display_name": "E. Morales-Campa\u00f1a", "orcid": null}, "institutions": [{"id": "https://openalex.org/I2802166871", "display_name": "Catholic University of the North", "ror": "https://ror.org/02akpm128", "country_code": "CL", "type": "education"}], "raw_affiliation_string": "[Instituto de Astronom\u00eda, Universidad Cat\u00f3lica del Norte, Av. Angamos 0610, Antofagasta, Chile]"}], "cited_by_count": 3, "biblio": {"volume": "626", "issue": null, "first_page": null, "last_page": null}, "is_retracted": false, "is_paratext": false, "concepts": [{"id": "https://openalex.org/C121332964", "wikidata": "https://www.wikidata.org/wiki/Q413", "display_name": "Physics", "level": 0, "score": "0.9082266"}, {"id": "https://openalex.org/C44870925", "wikidata": "https://www.wikidata.org/wiki/Q37547", "display_name": "Astrophysics", "level": 1, "score": "0.8419974"}, {"id": "https://openalex.org/C52348108", "wikidata": "https://www.wikidata.org/wiki/Q11387", "display_name": "Open cluster", "level": 3, "score": "0.72642386"}, {"id": "https://openalex.org/C150846664", "wikidata": "https://www.wikidata.org/wiki/Q7602306", "display_name": "Stars", "level": 2, "score": "0.6082378"}, {"id": "https://openalex.org/C66362828", "wikidata": "https://www.wikidata.org/wiki/Q208620", "display_name": "Hubble sequence", "level": 4, "score": "0.56930673"}, {"id": "https://openalex.org/C2779496878", "wikidata": "https://www.wikidata.org/wiki/Q42372", "display_name": "Nebula", "level": 3, "score": "0.5515235"}, {"id": "https://openalex.org/C2779343474", "wikidata": "https://www.wikidata.org/wiki/Q3109175", "display_name": "Context (archaeology)", "level": 2, "score": "0.5442666"}, {"id": "https://openalex.org/C164866538", "wikidata": "https://www.wikidata.org/wiki/Q367351", "display_name": "Cluster (spacecraft)", "level": 2, "score": "0.5018227"}, {"id": "https://openalex.org/C68271606", "wikidata": "https://www.wikidata.org/wiki/Q625648", "display_name": "Photometry (optics)", "level": 3, "score": "0.45252743"}, {"id": "https://openalex.org/C41074950", "wikidata": "https://www.wikidata.org/wiki/Q240105", "display_name": "Radial velocity", "level": 3, "score": "0.43970647"}, {"id": "https://openalex.org/C1276947", "wikidata": "https://www.wikidata.org/wiki/Q333", "display_name": "Astronomy", "level": 1, "score": "0.39515358"}], "mesh": [], "alternate_host_venues": [{"id": "https://openalex.org/V205231332", "display_name": "Astronomy and Astrophysics", "type": "journal", "url": "https://www.aanda.org/articles/aa/pdf/2019/06/aa35243-19.pdf", "is_oa": true, "version": "publishedVersion", "license": null}, {"id": null, "display_name": "arXiv", "type": "repository", "url": "http://arxiv.org/pdf/1906.09500", "is_oa": true, "version": "submittedVersion", "license": null}, {"id": null, "display_name": "Chiba Institute of Technology - Springer Link", "type": "repository", "url": "https://www.aanda.org/10.1051/0004-6361/201935243/pdf", "is_oa": true, "version": "submittedVersion", "license": null}, {"id": null, "display_name": "University of Padua - Padua Research Archive", "type": "repository", "url": "https://www.research.unipd.it/bitstream/11577/3303277/1/aa35243-19.pdf", "is_oa": true, "version": "submittedVersion", "license": null}], "referenced_works": ["https://openalex.org/W1579689779", "https://openalex.org/W1965337953", "https://openalex.org/W1978348925", "https://openalex.org/W1984788518", "https://openalex.org/W1987866504", "https://openalex.org/W1989803315", "https://openalex.org/W2004895727", "https://openalex.org/W2030196560", "https://openalex.org/W2040047395", "https://openalex.org/W2042114541", "https://openalex.org/W2051253522", "https://openalex.org/W2061765596", "https://openalex.org/W2080675603", "https://openalex.org/W2092101222", "https://openalex.org/W2108298827", "https://openalex.org/W2136093157", "https://openalex.org/W2170011509", "https://openalex.org/W2252367559", "https://openalex.org/W2562822224", "https://openalex.org/W2597993038", "https://openalex.org/W2601053151", "https://openalex.org/W2784067869", "https://openalex.org/W2798336535", "https://openalex.org/W2798433860", "https://openalex.org/W2799268730", "https://openalex.org/W2996098872", "https://openalex.org/W2998636648", "https://openalex.org/W3099258218", "https://openalex.org/W3101453606", "https://openalex.org/W3102784118", "https://openalex.org/W3103317324", "https://openalex.org/W3105726991", "https://openalex.org/W3110814193", "https://openalex.org/W3125764496"], "related_works": ["https://openalex.org/W1766445899", "https://openalex.org/W2010893298", "https://openalex.org/W2010952600", "https://openalex.org/W2052243076", "https://openalex.org/W2062562218", "https://openalex.org/W2077572213", "https://openalex.org/W2080660421", "https://openalex.org/W2084348530", "https://openalex.org/W2093946497", "https://openalex.org/W2094123159", "https://openalex.org/W2942707288", "https://openalex.org/W2963349857", "https://openalex.org/W3001446384", "https://openalex.org/W3100570689", "https://openalex.org/W3102985225", "https://openalex.org/W3103628882", "https://openalex.org/W3103664135", "https://openalex.org/W3103810319", "https://openalex.org/W3105690914"], "cited_by_api_url": "https://api.openalex.org/works?filter=cites:W3100151520", "counts_by_year": [{"year": 2021, "cited_by_count": 1}, {"year": 2020, "cited_by_count": 1}, {"year": 2019, "cited_by_count": 1}], "updated_date": "2022-07-29T01:27:04.751528", "created_date": "2020-11-23", "abstract_inverted_index": null, "indice": 406, "possible_astronomy": true}]